{
  "data": [
    {
      "id": "1",
      "body_html": null,
      "handle": "example-hat",
      "published_at": null,
      "status": {
        "label": "Archived",
        "value": "archived"
      },
      "tags": [
        "mens hat example"
      ],
      "title": "Example Hat",
      "vendor": "Snazzyway",
      "has_only_default_variant": false,
      "image": {
        "product_id": "1",
        "position": "1",
        "width": "5000",
        "height": "3333",
        "src": "https://boffinbrains.in/dropship/public/storage/dummy-products/kids-beanie.webp"
      },
      "options": [
        {
          "name": "Title",
          "product_id": "1",
          "position": "1",
          "values": [
            {
              "name": "Grey"
            }
          ]
        }
      ],
      "variants": [
        {
          "id": 1,
          "compare_at_price": "23",
          "grams": "275",
          "weight": "275.00",
          "weight_unit": "g",
          "inventory_policy": "deny",
          "inventory_available": "0",
          "inventory_unavailable": "0",
          "inventory_commited": "0",
          "inventory_on_hand": "0",
          "option1": "Grey",
          "option2": null,
          "option3": null,
          "position": "1",
          "price": "18",
          "product_id": "1",
          "product_image_id": null,
          "sku": null,
          "taxable": true,
          "title": "Grey",
          "harmonized_system_code": null,
          "country_code_of_origin": null,
          "province_code_of_origin": null,
          "product": {
            "id": 1,
            "body_html": null,
            "handle": "example-hat",
            "published_at": null,
            "status": {
              "label": "Archived",
              "value": "archived"
            },
            "tags": [
              "mens hat example"
            ],
            "title": "Example Hat",
            "vendor": "Snazzyway",
            "has_only_default_variant": false,
            "image": {
              "product_id": "1",
              "position": "1",
              "width": "5000",
              "height": "3333",
              "src": "https://boffinbrains.in/dropship/public/storage/dummy-products/kids-beanie.webp"
            }
          },
          "presentment": {
            "price": "₹18.00"
          }
        }
      ]
    },
    {
      "id": "2",
      "body_html": null,
      "handle": "example-pants",
      "published_at": null,
      "status": {
        "label": "Draft",
        "value": "draft"
      },
      "tags": [
        "mens pants example"
      ],
      "title": "Example Pants",
      "vendor": "Snazzyway",
      "has_only_default_variant": true,
      "image": {
        "product_id": "2",
        "position": "1",
        "width": "5000",
        "height": "3333",
        "src": "https://boffinbrains.in/dropship/public/storage/dummy-products/distressed-kids-jeans.webp"
      },
      "options": [
        {
          "name": "Title",
          "product_id": "2",
          "position": "1",
          "values": [
            {
              "name": "Jeans, W32H34"
            }
          ]
        }
      ],
      "variants": [
        {
          "id": 2,
          "compare_at_price": "50",
          "grams": "1250",
          "weight": "1250.00",
          "weight_unit": "g",
          "inventory_policy": "deny",
          "inventory_available": "0",
          "inventory_unavailable": "0",
          "inventory_commited": "0",
          "inventory_on_hand": "0",
          "option1": "Jeans, W32H34",
          "option2": null,
          "option3": null,
          "position": "1",
          "price": "58",
          "product_id": "2",
          "product_image_id": null,
          "sku": null,
          "taxable": true,
          "title": "Jeans, W32H34",
          "harmonized_system_code": null,
          "country_code_of_origin": null,
          "province_code_of_origin": null,
          "product": {
            "id": 2,
            "body_html": null,
            "handle": "example-pants",
            "published_at": null,
            "status": {
              "label": "Draft",
              "value": "draft"
            },
            "tags": [
              "mens pants example"
            ],
            "title": "Example Pants",
            "vendor": "Snazzyway",
            "has_only_default_variant": true,
            "image": {
              "product_id": "2",
              "position": "1",
              "width": "5000",
              "height": "3333",
              "src": "https://boffinbrains.in/dropship/public/storage/dummy-products/distressed-kids-jeans.webp"
            }
          },
          "presentment": {
            "price": "₹58.00"
          }
        }
      ]
    },
    {
      "id": "3",
      "body_html": null,
      "handle": "example-t-shirt",
      "published_at": "2024-03-18T16:26:40.000000Z",
      "status": {
        "label": "Active",
        "value": "active"
      },
      "tags": [
        "mens t-shirt example"
      ],
      "title": "Example T-Shirt",
      "vendor": "Snazzyway",
      "has_only_default_variant": false,
      "image": {
        "product_id": "3",
        "position": "1",
        "width": "5000",
        "height": "3333",
        "src": "https://boffinbrains.in/dropship/public/storage/dummy-products/green-t-shirt.webp"
      },
      "options": [
        {
          "name": "Title",
          "product_id": "3",
          "position": "1",
          "values": [
            {
              "name": "Lithograph - Height: 9\" x Width: 12\""
            },
            {
              "name": "Small"
            },
            {
              "name": "Medium"
            }
          ]
        }
      ],
      "variants": [
        {
          "id": 3,
          "compare_at_price": null,
          "grams": "3629",
          "weight": "3629.00",
          "weight_unit": "g",
          "inventory_policy": "deny",
          "inventory_available": "0",
          "inventory_unavailable": "0",
          "inventory_commited": "0",
          "inventory_on_hand": "0",
          "option1": "Lithograph - Height: 9\" x Width: 12\"",
          "option2": null,
          "option3": null,
          "position": "1",
          "price": "25",
          "product_id": "3",
          "product_image_id": null,
          "sku": null,
          "taxable": true,
          "title": "Lithograph - Height: 9\" x Width: 12\"",
          "harmonized_system_code": null,
          "country_code_of_origin": null,
          "province_code_of_origin": null,
          "product": {
            "id": 3,
            "body_html": null,
            "handle": "example-t-shirt",
            "published_at": "2024-03-18T16:26:40.000000Z",
            "status": {
              "label": "Active",
              "value": "active"
            },
            "tags": [
              "mens t-shirt example"
            ],
            "title": "Example T-Shirt",
            "vendor": "Snazzyway",
            "has_only_default_variant": false,
            "image": {
              "product_id": "3",
              "position": "1",
              "width": "5000",
              "height": "3333",
              "src": "https://boffinbrains.in/dropship/public/storage/dummy-products/green-t-shirt.webp"
            }
          },
          "presentment": {
            "price": "₹25.00"
          }
        },
        {
          "id": 4,
          "compare_at_price": "25",
          "grams": "200",
          "weight": "200.00",
          "weight_unit": "g",
          "inventory_policy": "deny",
          "inventory_available": "0",
          "inventory_unavailable": "0",
          "inventory_commited": "0",
          "inventory_on_hand": "0",
          "option1": "Small",
          "option2": null,
          "option3": null,
          "position": "2",
          "price": "20",
          "product_id": "3",
          "product_image_id": null,
          "sku": "example-shirt-s",
          "taxable": true,
          "title": "Small",
          "harmonized_system_code": null,
          "country_code_of_origin": null,
          "province_code_of_origin": null,
          "product": {
            "id": 3,
            "body_html": null,
            "handle": "example-t-shirt",
            "published_at": "2024-03-18T16:26:40.000000Z",
            "status": {
              "label": "Active",
              "value": "active"
            },
            "tags": [
              "mens t-shirt example"
            ],
            "title": "Example T-Shirt",
            "vendor": "Snazzyway",
            "has_only_default_variant": false,
            "image": {
              "product_id": "3",
              "position": "1",
              "width": "5000",
              "height": "3333",
              "src": "https://boffinbrains.in/dropship/public/storage/dummy-products/green-t-shirt.webp"
            }
          },
          "presentment": {
            "price": "₹20.00"
          }
        },
        {
          "id": 5,
          "compare_at_price": "25",
          "grams": "200",
          "weight": "200.00",
          "weight_unit": "g",
          "inventory_policy": "deny",
          "inventory_available": "0",
          "inventory_unavailable": "0",
          "inventory_commited": "0",
          "inventory_on_hand": "0",
          "option1": "Medium",
          "option2": null,
          "option3": null,
          "position": "3",
          "price": "20",
          "product_id": "3",
          "product_image_id": null,
          "sku": "example-shirt-m",
          "taxable": true,
          "title": "Medium",
          "harmonized_system_code": null,
          "country_code_of_origin": null,
          "province_code_of_origin": null,
          "product": {
            "id": 3,
            "body_html": null,
            "handle": "example-t-shirt",
            "published_at": "2024-03-18T16:26:40.000000Z",
            "status": {
              "label": "Active",
              "value": "active"
            },
            "tags": [
              "mens t-shirt example"
            ],
            "title": "Example T-Shirt",
            "vendor": "Snazzyway",
            "has_only_default_variant": false,
            "image": {
              "product_id": "3",
              "position": "1",
              "width": "5000",
              "height": "3333",
              "src": "https://boffinbrains.in/dropship/public/storage/dummy-products/green-t-shirt.webp"
            }
          },
          "presentment": {
            "price": "₹20.00"
          }
        }
      ]
    }
  ],
  "cart": []
}